{
  "중화정 (중식)": {
    "str" : "중화정은 중화요리 전문점입니다.\n\n[Tel]\n02-395-0236\n02-716-0236\n\n※ 수요일 휴무.\n\n[사진 크게 보기]\n",
    "img": "/menu/middle.jpg"
  },
  "북경 (중식)" : {
    "str" : "북경 중화요리 전문점입니다.\n\n[Tel]\n02-379-4544\n02-379-4100\n\n※ 월요일 휴무.\n\n[사진 크게 보기]\n",
    "img": "/menu/north.jpg"
  },
  "양자강 (중식)" : {
    "str" : "양자강은 중화요리 전문점입니다.\n\n[Tel]\n02-1577-3080\n\n[사진 크게 보기]\n",
    "img": "/menu/yang.jpg"
  },
  "이화원 (중식)" : {
    "str" : "이화원 중화요리 전문점입니다.\n\n[Tel]\n02-391-1003\n02-391-9908\n02-379-0960\n02-379-0961\n\n[사진 크게 보기]\n",
    "img": "/menu/leehwawon.jpg"
  },
  "야미가 (일식)" : {
    "str" : "야미가는 일식요리 전문점입니다.\n\n[Tel]\n02-722-1543\n02-722-1544\n\n※ 20:45 주문 마감.\n※ 만원이상 카드결제가능\n※ 1인분도 배달가능 (김치우동, 유부우동, 냉모밀은 제외)\n\n[사진 크게 보기]\n",
    "img": "/menu/ya.jpg"
  },
  "행복하우스 (한식)" : {
    "str" : "행복하우스는 한식 전문점입니다.\n\n[Tel]\n02-391-5030\n02-3217-5501\n\n※ 주말 휴무\n※ 오후 5시까지만 주문 받습니다.\n※ 11:30~12:30까지는 주문량이 많으니 미리 전화주시길 바랍니다.\n\n[사진 크게 보기]\n",
    "img": "/menu/happy.jpg"
  },
  "은혜식당 (한식)" : {
      "str" : "은혜식당은 한식 전문점입니다.\n\n[Tel]\n02-3217-4179\n\n[사진 크게 보기]\n",
      "img": "/menu/eun.jpg"
  },
  "수제 토마돈 치킨 (돈까스)" : {
    "str" : "수제 토마돈 치킨은 돈까스 전문점입니다.\n\n[Tel]\n02-391-8640\n010-8872-6967\n\n※ 배달영업시간 : 10:30~20:30\n※ 카드결제시 미리 말씀해주세요.\n\n[사진 크게 보기]\n",
    "img": "/menu/tomadon.jpg"
  },
  "신전떡볶이 (분식)" : {
    "str" : "신전떡볶이는 분식점입니다.\n\n[Tel]\n02-391-5890\n\n※ 영업시간 : 11:00~20:00\n※ 13,000원 이상 배달가능합니다.\n※공휴일과 일요일은 쉽니다.\n\n[사진 크게 보기]\n",
    "img": "/menu/sin.jpg"
  },
  "맥도날드 (패스트푸드)" : {
    "str" : "맥도날드는 패스트푸드 음식점입니다.\n\n[Tel]\n070-7209-0623\n\n※ 만원이상 주문가능\n\n[사진 크게 보기]\n",
    "img": "/menu/mc.jpg"
  }
}
